Metadata-Version: 2.1
Name: PyDInjector
Version: 1.0.2
Summary: Simple dependency injection container for python
Home-page: https://github.com/ivanmrosa/PYDInjector
Author: Ivan Muniz Rosa
Author-email: ivanmrosa@gmail.com
License: MIT License
Keywords: dependency injection,DI,inversion of control,IOC,container,Dependency Injection,Inversion of Control,Python
Platform: UNKNOWN
